Workbook

Sheet Start Here
A1: Retailer deduction triage worksheet | B1: Use the Claim Ledger tab for live line items.
A2: Purpose | B2: Triage remittance, debit note, or portal lines as supportable, missing proof, worth challenging, or Code risk.
A3: Method | B3: Pick the deduction type, enter delivery and claim dates, and let the matrix formulas fill the baseline verdict, evidence, Code check, and neutral query.
A4: Timing | B4: Shortfall and damaged-goods lines flag when the claim date is more than 30 days after delivery.
A5: Coverage | B5: The Deduction Type Matrix tab mirrors the JSON matrix used on the claims pages.

Sheet Claim Ledger
A1: Retailer | B1: Invoice / remittance date | C1: Delivery date | D1: Claim raised date | E1: Deduction type | F1: Reason note | G1: Amount | H1: Verdict | I1: Evidence | J1: Code check | K1: Neutral query | L1: Gap | M1: Priority | N1: Owner | O1: Status
G2: 0 | H2: =IF($E2="","",INDEX('Deduction Type Matrix'!$C$2:$C$17,MATCH($E2,'Deduction Type Matrix'!$A$2:$A$17,0))) | I2: =IF($E2="","",INDEX('Deduction Type Matrix'!$D$2:$D$17,MATCH($E2,'Deduction Type Matrix'!$A$2:$A$17,0))) | J2: =IF($E2="","",INDEX('Deduction Type Matrix'!$E$2:$E$17,MATCH($E2,'Deduction Type Matrix'!$A$2:$A$17,0))) | K2: =IF($E2="","",INDEX('Deduction Type Matrix'!$F$2:$F$17,MATCH($E2,'Deduction Type Matrix'!$A$2:$A$17,0))) | L2: =IF(AND(OR($E2="shortfall",$E2="damaged-goods"),$C2<>"",$D2<>"",$D2-$C2>30),"Claim raised more than 30 days after delivery.",IF($H2="missing proof","Await line-level proof from the retailer.",IF($H2="Code risk","Check Code coverage, agreement basis, and retailer conditions.",IF($H2="worth challenging","Reconcile this line against prior credits, timing, and support.","")))) | M2: =IF($E2="","",IF(AND(OR($E2="shortfall",$E2="damaged-goods"),$C2<>"",$D2<>"",$D2-$C2>30),"High",IF(OR($H2="Code risk",$G2>=5000),"High",IF(OR($H2="missing proof",$G2>=1000),"Medium","Low"))))
G3: 0 | H3: =IF($E3="","",INDEX('Deduction Type Matrix'!$C$2:$C$17,MATCH($E3,'Deduction Type Matrix'!$A$2:$A$17,0))) | I3: =IF($E3="","",INDEX('Deduction Type Matrix'!$D$2:$D$17,MATCH($E3,'Deduction Type Matrix'!$A$2:$A$17,0))) | J3: =IF($E3="","",INDEX('Deduction Type Matrix'!$E$2:$E$17,MATCH($E3,'Deduction Type Matrix'!$A$2:$A$17,0))) | K3: =IF($E3="","",INDEX('Deduction Type Matrix'!$F$2:$F$17,MATCH($E3,'Deduction Type Matrix'!$A$2:$A$17,0))) | L3: =IF(AND(OR($E3="shortfall",$E3="damaged-goods"),$C3<>"",$D3<>"",$D3-$C3>30),"Claim raised more than 30 days after delivery.",IF($H3="missing proof","Await line-level proof from the retailer.",IF($H3="Code risk","Check Code coverage, agreement basis, and retailer conditions.",IF($H3="worth challenging","Reconcile this line against prior credits, timing, and support.","")))) | M3: =IF($E3="","",IF(AND(OR($E3="shortfall",$E3="damaged-goods"),$C3<>"",$D3<>"",$D3-$C3>30),"High",IF(OR($H3="Code risk",$G3>=5000),"High",IF(OR($H3="missing proof",$G3>=1000),"Medium","Low"))))
G4: 0 | H4: =IF($E4="","",INDEX('Deduction Type Matrix'!$C$2:$C$17,MATCH($E4,'Deduction Type Matrix'!$A$2:$A$17,0))) | I4: =IF($E4="","",INDEX('Deduction Type Matrix'!$D$2:$D$17,MATCH($E4,'Deduction Type Matrix'!$A$2:$A$17,0))) | J4: =IF($E4="","",INDEX('Deduction Type Matrix'!$E$2:$E$17,MATCH($E4,'Deduction Type Matrix'!$A$2:$A$17,0))) | K4: =IF($E4="","",INDEX('Deduction Type Matrix'!$F$2:$F$17,MATCH($E4,'Deduction Type Matrix'!$A$2:$A$17,0))) | L4: =IF(AND(OR($E4="shortfall",$E4="damaged-goods"),$C4<>"",$D4<>"",$D4-$C4>30),"Claim raised more than 30 days after delivery.",IF($H4="missing proof","Await line-level proof from the retailer.",IF($H4="Code risk","Check Code coverage, agreement basis, and retailer conditions.",IF($H4="worth challenging","Reconcile this line against prior credits, timing, and support.","")))) | M4: =IF($E4="","",IF(AND(OR($E4="shortfall",$E4="damaged-goods"),$C4<>"",$D4<>"",$D4-$C4>30),"High",IF(OR($H4="Code risk",$G4>=5000),"High",IF(OR($H4="missing proof",$G4>=1000),"Medium","Low"))))
G5: 0 | H5: =IF($E5="","",INDEX('Deduction Type Matrix'!$C$2:$C$17,MATCH($E5,'Deduction Type Matrix'!$A$2:$A$17,0))) | I5: =IF($E5="","",INDEX('Deduction Type Matrix'!$D$2:$D$17,MATCH($E5,'Deduction Type Matrix'!$A$2:$A$17,0))) | J5: =IF($E5="","",INDEX('Deduction Type Matrix'!$E$2:$E$17,MATCH($E5,'Deduction Type Matrix'!$A$2:$A$17,0))) | K5: =IF($E5="","",INDEX('Deduction Type Matrix'!$F$2:$F$17,MATCH($E5,'Deduction Type Matrix'!$A$2:$A$17,0))) | L5: =IF(AND(OR($E5="shortfall",$E5="damaged-goods"),$C5<>"",$D5<>"",$D5-$C5>30),"Claim raised more than 30 days after delivery.",IF($H5="missing proof","Await line-level proof from the retailer.",IF($H5="Code risk","Check Code coverage, agreement basis, and retailer conditions.",IF($H5="worth challenging","Reconcile this line against prior credits, timing, and support.","")))) | M5: =IF($E5="","",IF(AND(OR($E5="shortfall",$E5="damaged-goods"),$C5<>"",$D5<>"",$D5-$C5>30),"High",IF(OR($H5="Code risk",$G5>=5000),"High",IF(OR($H5="missing proof",$G5>=1000),"Medium","Low"))))
G6: 0 | H6: =IF($E6="","",INDEX('Deduction Type Matrix'!$C$2:$C$17,MATCH($E6,'Deduction Type Matrix'!$A$2:$A$17,0))) | I6: =IF($E6="","",INDEX('Deduction Type Matrix'!$D$2:$D$17,MATCH($E6,'Deduction Type Matrix'!$A$2:$A$17,0))) | J6: =IF($E6="","",INDEX('Deduction Type Matrix'!$E$2:$E$17,MATCH($E6,'Deduction Type Matrix'!$A$2:$A$17,0))) | K6: =IF($E6="","",INDEX('Deduction Type Matrix'!$F$2:$F$17,MATCH($E6,'Deduction Type Matrix'!$A$2:$A$17,0))) | L6: =IF(AND(OR($E6="shortfall",$E6="damaged-goods"),$C6<>"",$D6<>"",$D6-$C6>30),"Claim raised more than 30 days after delivery.",IF($H6="missing proof","Await line-level proof from the retailer.",IF($H6="Code risk","Check Code coverage, agreement basis, and retailer conditions.",IF($H6="worth challenging","Reconcile this line against prior credits, timing, and support.","")))) | M6: =IF($E6="","",IF(AND(OR($E6="shortfall",$E6="damaged-goods"),$C6<>"",$D6<>"",$D6-$C6>30),"High",IF(OR($H6="Code risk",$G6>=5000),"High",IF(OR($H6="missing proof",$G6>=1000),"Medium","Low"))))
G7: 0 | H7: =IF($E7="","",INDEX('Deduction Type Matrix'!$C$2:$C$17,MATCH($E7,'Deduction Type Matrix'!$A$2:$A$17,0))) | I7: =IF($E7="","",INDEX('Deduction Type Matrix'!$D$2:$D$17,MATCH($E7,'Deduction Type Matrix'!$A$2:$A$17,0))) | J7: =IF($E7="","",INDEX('Deduction Type Matrix'!$E$2:$E$17,MATCH($E7,'Deduction Type Matrix'!$A$2:$A$17,0))) | K7: =IF($E7="","",INDEX('Deduction Type Matrix'!$F$2:$F$17,MATCH($E7,'Deduction Type Matrix'!$A$2:$A$17,0))) | L7: =IF(AND(OR($E7="shortfall",$E7="damaged-goods"),$C7<>"",$D7<>"",$D7-$C7>30),"Claim raised more than 30 days after delivery.",IF($H7="missing proof","Await line-level proof from the retailer.",IF($H7="Code risk","Check Code coverage, agreement basis, and retailer conditions.",IF($H7="worth challenging","Reconcile this line against prior credits, timing, and support.","")))) | M7: =IF($E7="","",IF(AND(OR($E7="shortfall",$E7="damaged-goods"),$C7<>"",$D7<>"",$D7-$C7>30),"High",IF(OR($H7="Code risk",$G7>=5000),"High",IF(OR($H7="missing proof",$G7>=1000),"Medium","Low"))))
G8: 0 | H8: =IF($E8="","",INDEX('Deduction Type Matrix'!$C$2:$C$17,MATCH($E8,'Deduction Type Matrix'!$A$2:$A$17,0))) | I8: =IF($E8="","",INDEX('Deduction Type Matrix'!$D$2:$D$17,MATCH($E8,'Deduction Type Matrix'!$A$2:$A$17,0))) | J8: =IF($E8="","",INDEX('Deduction Type Matrix'!$E$2:$E$17,MATCH($E8,'Deduction Type Matrix'!$A$2:$A$17,0))) | K8: =IF($E8="","",INDEX('Deduction Type Matrix'!$F$2:$F$17,MATCH($E8,'Deduction Type Matrix'!$A$2:$A$17,0))) | L8: =IF(AND(OR($E8="shortfall",$E8="damaged-goods"),$C8<>"",$D8<>"",$D8-$C8>30),"Claim raised more than 30 days after delivery.",IF($H8="missing proof","Await line-level proof from the retailer.",IF($H8="Code risk","Check Code coverage, agreement basis, and retailer conditions.",IF($H8="worth challenging","Reconcile this line against prior credits, timing, and support.","")))) | M8: =IF($E8="","",IF(AND(OR($E8="shortfall",$E8="damaged-goods"),$C8<>"",$D8<>"",$D8-$C8>30),"High",IF(OR($H8="Code risk",$G8>=5000),"High",IF(OR($H8="missing proof",$G8>=1000),"Medium","Low"))))
G9: 0 | H9: =IF($E9="","",INDEX('Deduction Type Matrix'!$C$2:$C$17,MATCH($E9,'Deduction Type Matrix'!$A$2:$A$17,0))) | I9: =IF($E9="","",INDEX('Deduction Type Matrix'!$D$2:$D$17,MATCH($E9,'Deduction Type Matrix'!$A$2:$A$17,0))) | J9: =IF($E9="","",INDEX('Deduction Type Matrix'!$E$2:$E$17,MATCH($E9,'Deduction Type Matrix'!$A$2:$A$17,0))) | K9: =IF($E9="","",INDEX('Deduction Type Matrix'!$F$2:$F$17,MATCH($E9,'Deduction Type Matrix'!$A$2:$A$17,0))) | L9: =IF(AND(OR($E9="shortfall",$E9="damaged-goods"),$C9<>"",$D9<>"",$D9-$C9>30),"Claim raised more than 30 days after delivery.",IF($H9="missing proof","Await line-level proof from the retailer.",IF($H9="Code risk","Check Code coverage, agreement basis, and retailer conditions.",IF($H9="worth challenging","Reconcile this line against prior credits, timing, and support.","")))) | M9: =IF($E9="","",IF(AND(OR($E9="shortfall",$E9="damaged-goods"),$C9<>"",$D9<>"",$D9-$C9>30),"High",IF(OR($H9="Code risk",$G9>=5000),"High",IF(OR($H9="missing proof",$G9>=1000),"Medium","Low"))))
G10: 0 | H10: =IF($E10="","",INDEX('Deduction Type Matrix'!$C$2:$C$17,MATCH($E10,'Deduction Type Matrix'!$A$2:$A$17,0))) | I10: =IF($E10="","",INDEX('Deduction Type Matrix'!$D$2:$D$17,MATCH($E10,'Deduction Type Matrix'!$A$2:$A$17,0))) | J10: =IF($E10="","",INDEX('Deduction Type Matrix'!$E$2:$E$17,MATCH($E10,'Deduction Type Matrix'!$A$2:$A$17,0))) | K10: =IF($E10="","",INDEX('Deduction Type Matrix'!$F$2:$F$17,MATCH($E10,'Deduction Type Matrix'!$A$2:$A$17,0))) | L10: =IF(AND(OR($E10="shortfall",$E10="damaged-goods"),$C10<>"",$D10<>"",$D10-$C10>30),"Claim raised more than 30 days after delivery.",IF($H10="missing proof","Await line-level proof from the retailer.",IF($H10="Code risk","Check Code coverage, agreement basis, and retailer conditions.",IF($H10="worth challenging","Reconcile this line against prior credits, timing, and support.","")))) | M10: =IF($E10="","",IF(AND(OR($E10="shortfall",$E10="damaged-goods"),$C10<>"",$D10<>"",$D10-$C10>30),"High",IF(OR($H10="Code risk",$G10>=5000),"High",IF(OR($H10="missing proof",$G10>=1000),"Medium","Low"))))
G11: 0 | H11: =IF($E11="","",INDEX('Deduction Type Matrix'!$C$2:$C$17,MATCH($E11,'Deduction Type Matrix'!$A$2:$A$17,0))) | I11: =IF($E11="","",INDEX('Deduction Type Matrix'!$D$2:$D$17,MATCH($E11,'Deduction Type Matrix'!$A$2:$A$17,0))) | J11: =IF($E11="","",INDEX('Deduction Type Matrix'!$E$2:$E$17,MATCH($E11,'Deduction Type Matrix'!$A$2:$A$17,0))) | K11: =IF($E11="","",INDEX('Deduction Type Matrix'!$F$2:$F$17,MATCH($E11,'Deduction Type Matrix'!$A$2:$A$17,0))) | L11: =IF(AND(OR($E11="shortfall",$E11="damaged-goods"),$C11<>"",$D11<>"",$D11-$C11>30),"Claim raised more than 30 days after delivery.",IF($H11="missing proof","Await line-level proof from the retailer.",IF($H11="Code risk","Check Code coverage, agreement basis, and retailer conditions.",IF($H11="worth challenging","Reconcile this line against prior credits, timing, and support.","")))) | M11: =IF($E11="","",IF(AND(OR($E11="shortfall",$E11="damaged-goods"),$C11<>"",$D11<>"",$D11-$C11>30),"High",IF(OR($H11="Code risk",$G11>=5000),"High",IF(OR($H11="missing proof",$G11>=1000),"Medium","Low"))))
G12: 0 | H12: =IF($E12="","",INDEX('Deduction Type Matrix'!$C$2:$C$17,MATCH($E12,'Deduction Type Matrix'!$A$2:$A$17,0))) | I12: =IF($E12="","",INDEX('Deduction Type Matrix'!$D$2:$D$17,MATCH($E12,'Deduction Type Matrix'!$A$2:$A$17,0))) | J12: =IF($E12="","",INDEX('Deduction Type Matrix'!$E$2:$E$17,MATCH($E12,'Deduction Type Matrix'!$A$2:$A$17,0))) | K12: =IF($E12="","",INDEX('Deduction Type Matrix'!$F$2:$F$17,MATCH($E12,'Deduction Type Matrix'!$A$2:$A$17,0))) | L12: =IF(AND(OR($E12="shortfall",$E12="damaged-goods"),$C12<>"",$D12<>"",$D12-$C12>30),"Claim raised more than 30 days after delivery.",IF($H12="missing proof","Await line-level proof from the retailer.",IF($H12="Code risk","Check Code coverage, agreement basis, and retailer conditions.",IF($H12="worth challenging","Reconcile this line against prior credits, timing, and support.","")))) | M12: =IF($E12="","",IF(AND(OR($E12="shortfall",$E12="damaged-goods"),$C12<>"",$D12<>"",$D12-$C12>30),"High",IF(OR($H12="Code risk",$G12>=5000),"High",IF(OR($H12="missing proof",$G12>=1000),"Medium","Low"))))
G13: 0 | H13: =IF($E13="","",INDEX('Deduction Type Matrix'!$C$2:$C$17,MATCH($E13,'Deduction Type Matrix'!$A$2:$A$17,0))) | I13: =IF($E13="","",INDEX('Deduction Type Matrix'!$D$2:$D$17,MATCH($E13,'Deduction Type Matrix'!$A$2:$A$17,0))) | J13: =IF($E13="","",INDEX('Deduction Type Matrix'!$E$2:$E$17,MATCH($E13,'Deduction Type Matrix'!$A$2:$A$17,0))) | K13: =IF($E13="","",INDEX('Deduction Type Matrix'!$F$2:$F$17,MATCH($E13,'Deduction Type Matrix'!$A$2:$A$17,0))) | L13: =IF(AND(OR($E13="shortfall",$E13="damaged-goods"),$C13<>"",$D13<>"",$D13-$C13>30),"Claim raised more than 30 days after delivery.",IF($H13="missing proof","Await line-level proof from the retailer.",IF($H13="Code risk","Check Code coverage, agreement basis, and retailer conditions.",IF($H13="worth challenging","Reconcile this line against prior credits, timing, and support.","")))) | M13: =IF($E13="","",IF(AND(OR($E13="shortfall",$E13="damaged-goods"),$C13<>"",$D13<>"",$D13-$C13>30),"High",IF(OR($H13="Code risk",$G13>=5000),"High",IF(OR($H13="missing proof",$G13>=1000),"Medium","Low"))))
... G41: 0 | H41: =IF($E41="","",INDEX('Deduction Type Matrix'!$C$2:$C$17,MATCH($E41,'Deduction Type Matrix'!$A$2:$A$17,0))) | I41: =IF($E41="","",INDEX('Deduction Type Matrix'!$D$2:$D$17,MATCH($E41,'Deduction Type Matrix'!$A$2:$A$17,0))) | J41: =IF($E41="","",INDEX('Deduction Type Matrix'!$E$2:$E$17,MATCH($E41,'Deduction Type Matrix'!$A$2:$A$17,0))) | K41: =IF($E41="","",INDEX('Deduction Type Matrix'!$F$2:$F$17,MATCH($E41,'Deduction Type Matrix'!$A$2:$A$17,0))) | L41: =IF(AND(OR($E41="shortfall",$E41="damaged-goods"),$C41<>"",$D41<>"",$D41-$C41>30),"Claim raised more than 30 days after delivery.",IF($H41="missing proof","Await line-level proof from the retailer.",IF($H41="Code risk","Check Code coverage, agreement basis, and retailer conditions.",IF($H41="worth challenging","Reconcile this line against prior credits, timing, and support.","")))) | M41: =IF($E41="","",IF(AND(OR($E41="shortfall",$E41="damaged-goods"),$C41<>"",$D41<>"",$D41-$C41>30),"High",IF(OR($H41="Code risk",$G41>=5000),"High",IF(OR($H41="missing proof",$G41>=1000),"Medium","Low"))))

Sheet Deduction Type Matrix
A1: id | B1: label | C1: default verdict | D1: short evidence | E1: Code check | F1: neutral query | G1: deadline helper | H1: family | I1: deadline rule | J1: deadline days
A2: difot-penalty | B2: DIFOT penalty | C2: missing proof | D2: PO, ASN, booked window, POD, dock timestamp, retailer scorecard. | E2: Usually an evidence issue, not a Code issue. | F2: Please provide the DIFOT scorecard line, booked-window basis, dock timestamp, and calculation used for this deduction. | G2: Check the retailer portal claims article and your supply agreement for the dispute window. | H2: DIFOT / OTIF
A3: otif-penalty | B3: OTIF penalty | C3: missing proof | D3: PO, ASN, booked window, POD, dock timestamp, retailer scorecard. | E3: Usually an evidence issue, not a Code issue. | F3: Please provide the OTIF scorecard line, booked-window basis, dock timestamp, and calculation used for this deduction. | G3: Check the retailer portal claims article and your supply agreement for the dispute window. | H3: DIFOT / OTIF
A4: promo-scan-rebate | B4: Promo scan / rebate | C4: missing proof | D4: Promo agreement, SKU scope, store/banner scope, scan report, rate, period. | E4: Check agreed funding, scope, and reasonableness. | F4: Please provide the scan report by SKU, store group, and promo dates used to calculate this deduction. | G4: Check the retailer portal claims article and your promo agreement. | H4: Promotion funding
A5: shrinkage | B5: Shrinkage | C5: Code risk | D5: Claim reason, possession point, supply agreement clause, retailer basis. | E5: Code risk if the retailer is Code-covered and the loss is post-possession. | F5: Please identify the basis for charging this shrinkage amount to us, including the possession point and any clause relied on. | G5: Confirm whether the retailer is Code-covered and when possession passed. | H5: Code-sensitive claims
A6: shortfall | B6: Shortfall / short-delivery | C6: missing proof | D6: POD, delivery docket, ASN, retailer received quantity, claim date. | E6: Check the Code's 30-day cap on retailer-raised shortfall claims. | F6: Please provide the received-quantity evidence and the delivery date used for this shortfall claim. | G6: The Code caps retailer-raised shortfall claims at no later than 30 days after delivery where the Code applies. | H6: Delivery variance | I6: claimRaisedWithinDays | J6: 30
A7: damaged-goods | B7: Damaged goods | C7: missing proof | D7: POD condition notes, photos, carrier report, warehouse notes, claim date. | E7: Check the Code's 30-day cap on retailer-raised damage claims. | F7: Please provide the delivery date, claim date, and damage evidence used for this claim. | G7: The Code caps retailer-raised damage claims at no later than 30 days after delivery where the Code applies. | H7: Delivery variance | I7: claimRaisedWithinDays | J7: 30
A8: wastage | B8: Wastage | C8: Code risk | D8: Wastage clause, calculation method, actual cost basis, mitigation evidence. | E8: Check express agreement, reasonable amount, stated calculation, and retailer cost mitigation. | F8: Please provide the agreed wastage clause, calculation method, actual cost basis, and steps taken to reduce the cost. | G8: Check the supply agreement and retailer portal claim window. | H8: Code-sensitive claims
A9: set-off | B9: Set-off | C9: Code risk | D9: Written consent or set-off clause, amount basis, debit note. | E9: Check written consent, agreement basis, and reasonableness. | F9: Please provide the written consent or supply agreement basis relied on for this set-off, plus the amount calculation. | G9: Check the supply agreement, trading terms, and retailer portal claim window. | H9: Code-sensitive claims
A10: post-audit-claim | B10: Post-audit claim | C10: missing proof | D10: Original PO, invoice, price list, promo agreement, prior remittance. | E10: Check whether the set-off or charge basis is allowed by agreement and reasonable. | F10: Please provide the transaction trail and agreement basis used for this post-audit claim. | G10: Check the trading terms, supply agreement, and portal window for historic claims. | H10: Historic claims
A11: duplicate-already-credited | B11: Duplicate / already credited | C11: worth challenging | D11: Prior remittance, debit note, credit note, claim ID, invoice history. | E11: Usually an evidence issue, not a Code issue. | F11: Please confirm whether this claim has already been deducted, set off, or credited, and provide the claim ID history. | G11: Check the retailer portal claim window and your credit note history. | H11: Duplicate claims
A12: overpricing-price-discrepancy | B12: Overpricing / price discrepancy | C12: missing proof | D12: PO, agreed price list, invoice, effective-date evidence. | E12: Usually an evidence issue, not a Code issue. | F12: Please provide the agreed price and effective date used to calculate this price discrepancy. | G12: Check the retailer portal claim window and price-change terms. | H12: Price variance
A13: pallet-packaging-charge | B13: Pallet / packaging charge | C13: missing proof | D13: Pallet transfer records, CHEP or Loscam statements, agreement, delivery docket. | E13: Check agreed basis and amount reasonableness where the Code applies. | F13: Please provide the pallet or packaging transfer records and agreement basis used for this charge. | G13: Check the retailer portal claim window; some equipment windows are separate from trade deductions. | H13: Operational charges
A14: freight-transport-deduction | B14: Freight / transport deduction | C14: missing proof | D14: Freight terms, carrier invoice, PO, delivery evidence. | E14: Check agreed basis and amount reasonableness where the Code applies. | F14: Please provide the freight terms, carrier evidence, and calculation used for this deduction. | G14: Check the supply agreement and retailer portal claim window. | H14: Operational charges
A15: listing-ranging-fee | B15: Listing / ranging fee | C15: Code risk | D15: Trading terms, listing or ranging agreement, SKU evidence, claim note. | E15: Check express written agreement and reasonableness. | F15: Please provide the express written agreement and amount basis used for this listing or ranging charge. | G15: Check the supply agreement, trading terms, and retailer portal claim window. | H15: Trade spend
A16: retail-media-activity-charge | B16: Retail media / activity charge | C16: missing proof | D16: Booking confirmation, activity proof, agreement, invoice or debit note. | E16: Check express agreement, delivery proof, and amount basis. | F16: Please provide the booking confirmation, activity proof, and agreed amount basis for this activity charge. | G16: Check the campaign agreement and retailer portal claim window. | H16: Trade spend
A17: asn-edi-barcode-compliance | B17: ASN / EDI / barcode compliance charge | C17: missing proof | D17: ASN log, EDI acknowledgement, label proof, warehouse receipt. | E17: Usually an evidence issue, not a Code issue. | F17: Please provide the ASN, EDI, barcode, or label error evidence used for this compliance charge. | G17: Check the retailer portal claim window and compliance-charge terms. | H17: Compliance charges

Sheet Summary
A1: Verdict | B1: Total amount
A2: supportable | B2: =SUMIF('Claim Ledger'!$H$2:$H$41,A2,'Claim Ledger'!$G$2:$G$41)
A3: missing proof | B3: =SUMIF('Claim Ledger'!$H$2:$H$41,A3,'Claim Ledger'!$G$2:$G$41)
A4: worth challenging | B4: =SUMIF('Claim Ledger'!$H$2:$H$41,A4,'Claim Ledger'!$G$2:$G$41)
A5: Code risk | B5: =SUMIF('Claim Ledger'!$H$2:$H$41,A5,'Claim Ledger'!$G$2:$G$41)
A7: Claims Desk handoff
A8: Send one redacted remittance with claim IDs, line notes, evidence gaps, and the neutral query text you want reviewed.
